{
    "variables": {
    "newMarkets": false,
    "amountOfNewMarkets": 18,
    "epochs": true,
    "amountOfNewEpochs": 18,
    "totalAmountOfEmittedTokens": 0,
    "isTestEnv": false
    },


    "markets": [
		{
			"name": "y2kTUSD_991_WETH*",
			"strikePrice": "991000000000000000",
			"token": "0x4d15a3a2286d883af0aa1b3f21367843fac63e07",
			"depositAsset": "WETH",
			"oracle":"0x6fAbee62266Da6686EE2744C6f15bb8352d2f28D",
			"depositFee": 0,
			"isGenericController": false, 
			"isDepegCondition": true, 
			"minQueueDeposit": "25000000000000000", 
			"relayFee": "200000000000000", 		
			"uri": "https://y2k.finance"
		},
		{
			"name": "y2kMAI_710_WETH*",
			"strikePrice": "710000000000000000",
			"token": "0x3f56e0c36d275367b8c502090edf38289b3dea0d",
			"depositAsset": "WETH",
			"oracle":"0x8De3c5148F13Bc33Bc1D7c9190186Ce163E15aB0",
			"depositFee": 0,
			"isGenericController": false, 
			"isDepegCondition": true, 
			"minQueueDeposit": "25000000000000000", 
			"relayFee": "200000000000000", 		
			"uri": "https://y2k.finance"
        },
		{
			"name": "y2kVST_984_WETH*",
			"strikePrice": "984000000000000000",
			"token": "0x64343594ab9b56e99087bfa6f2335db24c2d1f17",
			"depositAsset": "WETH",
			"oracle":"0x7531B3fB1AAaC7A86592C080866F622E80ECC8Cb",
			"depositFee": 0,
			"isGenericController": true, 
			"isDepegCondition": true, 
			"minQueueDeposit": "25000000000000000", 
			"relayFee": "200000000000000", 		
			"uri": "https://y2k.finance"
        },
		{
			"name": "y2kBUSD_998_WETH*",
			"strikePrice": "998000000000000000",
			"token": "0x4fabb145d64652a948d72533023f6e7a623c7c53",
			"depositAsset": "WETH",
			"oracle": "0x8FCb0F3715A82D83270777b3a5f3a7CF95Ce8Eec",
			"depositFee": 0,
			"isGenericController": false, 
			"isDepegCondition": true, 
			"minQueueDeposit": "25000000000000000", 
			"relayFee": "200000000000000", 	
			"uri": "https://y2k.finance"
		},
		{
			"name": "y2kBUSD_998_ARB*",
			"strikePrice": "998000000000000000",
			"token": "0x4fabb145d64652a948d72533023f6e7a623c7c53",
			"depositAsset": "ARB",
			"oracle": "0x8FCb0F3715A82D83270777b3a5f3a7CF95Ce8Eec",
			"depositFee": 0,
			"isGenericController": false, 
			"isDepegCondition": true, 
			"minQueueDeposit": "50000000000000000000", 
			"relayFee": "500000000000000000", 	
			"uri": "https://y2k.finance"
		},
		{
			"name": "y2kstETH_981_WETH*",
			"strikePrice": "981000000000000000",
			"token": "0xae7ab96520de3a18e5e111b5eaab095312d7fe84",
			"depositAsset": "WETH",
			"oracle": "0xded2c52b75B24732e9107377B7Ba93eC1fFa4BAf",
			"depositFee": 0,
			"isGenericController": false, 
			"isDepegCondition": true, 
			"minQueueDeposit": "25000000000000000", 
			"relayFee": "200000000000000", 	
			"uri": "https://y2k.finance"
		},
		{ 
			"name": "y2kstETH_981_ARB*",
			"strikePrice": "981000000000000000",
			"token": "0xae7ab96520de3a18e5e111b5eaab095312d7fe84",
			"depositAsset": "ARB",
			"oracle": "0xded2c52b75B24732e9107377B7Ba93eC1fFa4BAf",
			"depositFee": 0,
			"isGenericController": false, 
			"isDepegCondition": true, 
			"minQueueDeposit": "50000000000000000000", 
			"relayFee": "500000000000000000", 	
			"uri": "https://y2k.finance"
		},
		{
			"name": "y2kUSDD_985_WETH*",
			"strikePrice": "985000000000000000",
			"token": "0x680447595e8b7b3aa1b43beb9f6098c79ac2ab3f",
			"depositAsset": "WETH",
			"oracle":"0x4Ee1f9ec1048979930aC832a3C1d18a0b4955a02",
			"depositFee": 0,
			"isGenericController": false, 
			"isDepegCondition": true, 
			"minQueueDeposit": "25000000000000000", 
			"relayFee": "200000000000000", 	
			"uri": "https://y2k.finance"
		},
		{
			"name": "y2kUSDD_985_ARB*",
			"strikePrice": "985000000000000000",
			"token": "0x680447595e8b7b3aa1b43beb9f6098c79ac2ab3f",
			"depositAsset": "ARB",
			"oracle":"0x4Ee1f9ec1048979930aC832a3C1d18a0b4955a02",
			"depositFee": 0,
			"isGenericController": false, 
			"isDepegCondition": true, 
			"minQueueDeposit": "50000000000000000000", 
			"relayFee": "500000000000000000", 	
			"uri": "https://y2k.finance"
		},	
		{
			"name": "y2kDAI_998_WETH*",
			"strikePrice": "998000000000000000",
			"token": "0xDA10009cBd5D07dd0CeCc66161FC93D7c9000da1",
			"depositAsset": "WETH",
			"oracle": "0xc5C8E77B397E531B8EC06BFb0048328B30E9eCfB",
			"depositFee": 0,
			"isGenericController": false, 
			"isDepegCondition": true, 
			"minQueueDeposit": "25000000000000000", 
			"relayFee": "200000000000000", 	
			"uri": "https://y2k.finance"
		},
		{
			"name": "y2kFRAX_950_WETH*",
			"strikePrice": "950000000000000000",
			"token": "0x17fc002b466eec40dae837fc4be5c67993ddbd6f",
			"depositAsset": "WETH",
			"oracle": "0x0809E3d38d1B4214958faf06D8b1B1a2b73f2ab8",
			"depositFee": 0,
			"isGenericController": false, 
			"isDepegCondition": true, 
			"minQueueDeposit": "25000000000000000", 
			"relayFee": "200000000000000", 	
			"uri": "https://y2k.finance"
		},
		{
			"name": "y2kFRAX_990_WETH*",
			"strikePrice": "990000000000000000",
			"token": "0x17fc002b466eec40dae837fc4be5c67993ddbd6f",
			"depositAsset": "WETH",
			"oracle": "0x0809E3d38d1B4214958faf06D8b1B1a2b73f2ab8",
			"depositFee": 0,
			"isGenericController": false, 
			"isDepegCondition": true, 
			"minQueueDeposit": "25000000000000000", 
			"relayFee": "200000000000000", 	
			"uri": "https://y2k.finance"
		},
		{
			"name": "y2kLUSD_990_WETH*",
			"strikePrice": "990000000000000000",
			"token": "0x5f98805a4e8be255a32880fdec7f6728c6568ba0",
			"depositAsset": "WETH",
			"oracle":"0x0411D28c94d85A36bC72Cb0f875dfA8371D8fFfF",
			"depositFee": 0,
			"isGenericController": false, 
			"isDepegCondition": true, 
			"minQueueDeposit": "25000000000000000", 
			"relayFee": "200000000000000", 	
			"uri": "https://y2k.finance"
		},
		{
			"name": "y2kUSDC_992_WETH*",
			"strikePrice": "992000000000000000",
			"token": "0xFF970A61A04b1cA14834A43f5dE4533eBDDB5CC8",
			"depositAsset": "WETH",
			"oracle": "0x50834F3163758fcC1Df9973b6e91f0F0F0434aD3",
			"depositFee": 0,
			"isGenericController": false, 
			"isDepegCondition": true, 
			"minQueueDeposit": "25000000000000000", 
			"relayFee": "200000000000000", 	
			"uri": "https://y2k.finance"
		},
		{
			"name": "y2kUSDT_985_WETH*",
			"strikePrice": "985000000000000000",
			"token": "0xfd086bc7cd5c481dcc9c85ebe478a1c0b69fcbb9",
			"depositAsset": "WETH",
			"oracle": "0x3f3f5dF88dC9F13eac63DF89EC16ef6e7E25DdE7",
			"depositFee": 0,
			"isGenericController": false, 
			"isDepegCondition": true, 
			"minQueueDeposit": "25000000000000000", 
			"relayFee": "200000000000000", 	
			"uri": "https://y2k.finance"
		},
		{
			"name": "y2kUSDT_991_WETH*",
			"strikePrice": "991000000000000000",
			"token": "0xfd086bc7cd5c481dcc9c85ebe478a1c0b69fcbb9",
			"depositAsset": "WETH",
			"oracle":"0x3f3f5dF88dC9F13eac63DF89EC16ef6e7E25DdE7",
			"depositFee": 0,
			"isGenericController": false, 
			"isDepegCondition": true, 
			"minQueueDeposit": "25000000000000000", 
			"relayFee": "200000000000000", 	
			"uri": "https://y2k.finance"
		},
		{
			"name": "y2kWBTC_997_WETH*",
			"strikePrice": "997000000000000000",
			"token": "0x2260FAC5E5542a773Aa44fBCfeDf7C193bc2C599",
			"depositAsset": "WETH",
			"oracle": "0x0017abac5b6f291f9164e35b1234ca1d697f9cf4", 
			"depositFee": 0,
			"isGenericController": false, 
			"isDepegCondition": true, 
			"minQueueDeposit": "25000000000000000", 
			"relayFee": "200000000000000", 	
			"uri": "https://y2k.finance"
		},
		{
			"name": "y2kMIM_981_WETH*",
			"strikePrice": "981000000000000000",
			"token": "0xFEa7a6a0B346362BF88A9e4A88416B77a57D6c2A",
			"depositAsset": "WETH",
			"oracle": "0x87121F6c9A9F6E90E59591E4Cf4804873f54A95b",
			"depositFee": 0,
			"isGenericController": false, 
			"isDepegCondition": true, 
			"minQueueDeposit": "25000000000000000", 
			"relayFee": "200000000000000", 	
			"uri": "https://y2k.finance"
		}
    ],
    "epochs": [
		{
			"name": "y2kTUSD_991_WETH*",
			"strikePrice": "991000000000000000",
			"token": "0x4d15a3a2286d883af0aa1b3f21367843fac63e07",
			"depositAsset": "WETH",
			"epochBegin": 1698192000,
			"epochEnd": 1698624000,
			"collatEmissions": "56818181818200000000",
			"premiumEmissions": "511363636364000000000",
			"withdrawalFee": 500
		},
		{
			"name": "y2kMAI_710_WETH*",
			"strikePrice": "710000000000000000",
			"token": "0x3f56e0c36d275367b8c502090edf38289b3dea0d",
			"depositAsset": "WETH",
			"epochBegin": 1698192000,
			"epochEnd": 1698624000,
			"collatEmissions": "56818181818200000000",
			"premiumEmissions": "511363636364000000000",
			"withdrawalFee": 500
		},
		{
			"name": "y2kVST_984_WETH*",
			"strikePrice": "984000000000000000",
			"token": "0x64343594ab9b56e99087bfa6f2335db24c2d1f17",
			"depositAsset": "WETH",
			"epochBegin": 1698192000,
			"epochEnd": 1698624000,
			"collatEmissions": "56818181818200000000",
			"premiumEmissions": "511363636364000000000",
			"withdrawalFee": 500
		},
		{
			"name": "y2kBUSD_998_WETH*",
			"strikePrice": "998000000000000000",
			"token": "0x4fabb145d64652a948d72533023f6e7a623c7c53",
			"depositAsset": "WETH",
			"epochBegin": 1698192000,
			"epochEnd": 1698624000,
			"collatEmissions": "56818181818200000000",
			"premiumEmissions": "511363636364000000000",
			"withdrawalFee": 500
		},
		{
			"name": "y2kBUSD_998_ARB*",
			"strikePrice": "998000000000000000",
			"token": "0x4fabb145d64652a948d72533023f6e7a623c7c53",
			"depositAsset": "ARB",
			"epochBegin": 1698192000,
			"epochEnd": 1698624000,
			"collatEmissions": "56818181818200000000",
			"premiumEmissions": "511363636364000000000",
			"withdrawalFee": 500
		},
		{
			"name": "y2kstETH_981_WETH*",
			"strikePrice": "981000000000000000",
			"token": "0xae7ab96520de3a18e5e111b5eaab095312d7fe84",
			"depositAsset": "WETH",
			"epochBegin": 1698192000,
			"epochEnd": 1698624000,
			"collatEmissions": "56818181818200000000",
			"premiumEmissions": "511363636364000000000",
			"withdrawalFee": 500
		},
		{ 
			"name": "y2kstETH_981_ARB*",
			"strikePrice": "981000000000000000",
			"token": "0xae7ab96520de3a18e5e111b5eaab095312d7fe84",
			"depositAsset": "ARB",
			"epochBegin": 1698192000,
			"epochEnd": 1698624000,
			"collatEmissions": "56818181818200000000",
			"premiumEmissions": "511363636364000000000",
			"withdrawalFee": 500
		},
		{
			"name": "y2kUSDD_985_WETH*",
			"strikePrice": "985000000000000000",
			"token": "0x680447595e8b7b3aa1b43beb9f6098c79ac2ab3f",
			"depositAsset": "WETH",
			"epochBegin": 1698192000,
			"epochEnd": 1698624000,
			"collatEmissions": "56818181818200000000",
			"premiumEmissions": "511363636364000000000",
			"withdrawalFee": 500
		},
		{
			"name": "y2kUSDD_985_ARB*",
			"strikePrice": "985000000000000000",
			"token": "0x680447595e8b7b3aa1b43beb9f6098c79ac2ab3f",
			"depositAsset": "ARB",
			"epochBegin": 1698192000,
			"epochEnd": 1698624000,
			"collatEmissions": "56818181818200000000",
			"premiumEmissions": "511363636364000000000",
			"withdrawalFee": 500
		},	
		{
			"name": "y2kDAI_998_WETH*",
			"strikePrice": "998000000000000000",
			"token": "0xDA10009cBd5D07dd0CeCc66161FC93D7c9000da1",
			"depositAsset": "WETH",
			"epochBegin": 1698192000,
			"epochEnd": 1698624000,
			"collatEmissions": "56818181818200000000",
			"premiumEmissions": "511363636364000000000",
			"withdrawalFee": 500
		},
		{
			"name": "y2kFRAX_950_WETH*",
			"strikePrice": "950000000000000000",
			"token": "0x17fc002b466eec40dae837fc4be5c67993ddbd6f",
			"depositAsset": "WETH",
			"epochBegin": 1698192000,
			"epochEnd": 1698624000,
			"collatEmissions": "56818181818200000000",
			"premiumEmissions": "511363636364000000000",
			"withdrawalFee": 500
		},
		{
			"name": "y2kFRAX_990_WETH*",
			"strikePrice": "990000000000000000",
			"token": "0x17fc002b466eec40dae837fc4be5c67993ddbd6f",
			"depositAsset": "WETH",
			"epochBegin": 1698192000,
			"epochEnd": 1698624000,
			"collatEmissions": "56818181818200000000",
			"premiumEmissions": "511363636364000000000",
			"withdrawalFee": 500
		},
		{
			"name": "y2kLUSD_990_WETH*",
			"strikePrice": "990000000000000000",
			"token": "0x5f98805a4e8be255a32880fdec7f6728c6568ba0",
			"depositAsset": "WETH",
			"epochBegin": 1698192000,
			"epochEnd": 1698624000,
			"collatEmissions": "56818181818200000000",
			"premiumEmissions": "511363636364000000000",
			"withdrawalFee": 500
		},
		{
			"name": "y2kUSDC_992_WETH*",
			"strikePrice": "992000000000000000",
			"token": "0xFF970A61A04b1cA14834A43f5dE4533eBDDB5CC8",
			"depositAsset": "WETH",
			"epochBegin": 1698192000,
			"epochEnd": 1698624000,
			"collatEmissions": "56818181818200000000",
			"premiumEmissions": "511363636364000000000",
			"withdrawalFee": 500
		},
		{
			"name": "y2kUSDT_985_WETH*",
			"strikePrice": "985000000000000000",
			"token": "0xfd086bc7cd5c481dcc9c85ebe478a1c0b69fcbb9",
			"depositAsset": "WETH",
			"epochBegin": 1698192000,
			"epochEnd": 1698624000,
			"collatEmissions": "56818181818200000000",
			"premiumEmissions": "511363636364000000000",
			"withdrawalFee": 500
		},
		{
			"name": "y2kUSDT_991_WETH*",
			"strikePrice": "991000000000000000",
			"token": "0xfd086bc7cd5c481dcc9c85ebe478a1c0b69fcbb9",
			"depositAsset": "WETH",
			"epochBegin": 1698192000,
			"epochEnd": 1698624000,
			"collatEmissions": "56818181818200000000",
			"premiumEmissions": "511363636364000000000",
			"withdrawalFee": 500
		},
		{
			"name": "y2kWBTC_997_WETH*",
			"strikePrice": "997000000000000000",
			"token": "0x2260FAC5E5542a773Aa44fBCfeDf7C193bc2C599",
			"depositAsset": "WETH",
			"epochBegin": 1698192000,
			"epochEnd": 1698624000,
			"collatEmissions": "56818181818200000000",
			"premiumEmissions": "511363636364000000000",
			"withdrawalFee": 500
		},
		{
			"name": "y2kMIM_981_WETH*",
			"strikePrice": "981000000000000000",
			"token": "0xFEa7a6a0B346362BF88A9e4A88416B77a57D6c2A",
			"depositAsset": "WETH",
			"epochBegin": 1698192000,
			"epochEnd": 1698624000,
			"collatEmissions": "56818181818200000000",
			"premiumEmissions": "511363636364000000000",
			"withdrawalFee": 500
		}
    ]
   }