{

    "variables":{
        "newMarkets": true,
        "amountOfNewMarkets": 2,
        "marketsIds": [19,20],
        "newEpochs": true,
        "amountOfNewEpochs": 12,
        "epochsIds": [6, 7, 8, 12, 13, 14, 15, 16, 17, 18, 19, 20],
        "amountOfNewFarms": 12,
        "newFarms": true,
        "farmsIds" : [6, 7, 8, 12, 13, 14, 15, 16, 17, 18, 19, 20]
    },

    "markets":[
        {
            "marketId": 19,
            "name":"y2kBUSD_998*",
            "strikePrice": 998000000000000000,
            "token": "0x4Fabb145d64652a948d72533023f6E7A623C7C53",
            "oracle": "0x8fcb0f3715a82d83270777b3a5f3a7cf95ce8eec"       
        },
        {
            "marketId": 20,
            "name":"y2kSTETH_982*",
            "strikePrice": 982000000000000000,
            "token": "0x5979D7b546E38E414F7E9822514be443A4800529",
            "oracle": "0xf78D7cf5e2985DeB0E3EB7D0Dd0537d0003A8205"       
        }
    ],

    "epochs":[
        {
            "marketId": 6,
            "epochBegin":1676419200,
            "epochEnd":1676851200,
            "epochFee":50
        },
        {
            "marketId": 7,
            "epochBegin":1676419200,
            "epochEnd":1676851200,
            "epochFee":50
        },
        {
            "marketId": 8,
            "epochBegin":1676419200,
            "epochEnd":1676851200,
            "epochFee":50
        },
        {
            "marketId": 12,
            "epochBegin":1676419200,
            "epochEnd":1678838400,
            "epochFee":50
        },
        {
            "marketId": 13,
            "epochBegin":1676419200,
            "epochEnd":1676851200,
            "epochFee":50
        },
        {
            "marketId": 14,
            "epochBegin":1676419200,
            "epochEnd":1676851200,
            "epochFee":50
        },
        {
            "marketId": 15,
            "epochBegin":1676419200,
            "epochEnd":1678838400,
            "epochFee":50
        },
        {
            "marketId": 16,
            "epochBegin":1676419200,
            "epochEnd":1676851200,
            "epochFee":50
        },
        {
            "marketId": 17,
            "epochBegin":1676419200,
            "epochEnd":1676851200,
            "epochFee":50
        },
        {
            "marketId": 18,
            "epochBegin":1676419200,
            "epochEnd":1678838400,
            "epochFee":50
        },
        {
            "marketId": 19,
            "epochBegin":1676419200,
            "epochEnd":1678838400,
            "epochFee":50
        },
        {
            "marketId": 20,
            "epochBegin":1676419200,
            "epochEnd":1676851200,
            "epochFee":50
        }
    ],

    "farms":[
        {
            "marketId": 6,
            "epochEnd":1676851200,
            "farmRewardsHEDGE":"1406250000000000000000",
            "farmRewardsRISK" :"156250000000000000000"
        },
        {
            "marketId": 7,
            "epochEnd":1676851200,
            "farmRewardsHEDGE":"1406250000000000000000",
            "farmRewardsRISK" :"156250000000000000000"
        },
        {
            "marketId": 8,
            "epochEnd":1676851200,
            "farmRewardsHEDGE": "1406250000000000000000",
            "farmRewardsRISK" : "156250000000000000000"
        },
        {
            "marketId": 12,
            "epochEnd":1678838400,
            "farmRewardsHEDGE":"2812500000000000000000",
            "farmRewardsRISK" :"312500000000000000000"
        },
        {
            "marketId": 13,
            "epochEnd":1676851200,
            "farmRewardsHEDGE":"1406250000000000000000",
            "farmRewardsRISK" :"156250000000000000000"
        },
        {
            "marketId": 14,
            "epochEnd":1676851200,
            "farmRewardsHEDGE": "1406250000000000000000",
            "farmRewardsRISK" : "156250000000000000000"
        },
        {
            "marketId": 15,
            "epochEnd":1678838400,
            "farmRewardsHEDGE":"2812500000000000000000",
            "farmRewardsRISK" :"312500000000000000000"
        },
        {
            "marketId": 16,
            "epochEnd":1676851200,
            "farmRewardsHEDGE":"1406250000000000000000",
            "farmRewardsRISK" :"156250000000000000000"
        },
        {
            "marketId": 17,
            "epochEnd":1676851200,
            "farmRewardsHEDGE":"1406250000000000000000",
            "farmRewardsRISK" :"156250000000000000000"
        },
        {
            "marketId": 18,
            "epochEnd":1678838400,
            "farmRewardsHEDGE":"2812500000000000000000",
            "farmRewardsRISK" :"312500000000000000000"
        },
        {
            "marketId": 19,
            "epochEnd":1678838400,
            "farmRewardsHEDGE":"2812500000000000000000",
            "farmRewardsRISK" :"312500000000000000000"
        },
        {
            "marketId": 20,
            "epochEnd":1676851200,
            "farmRewardsHEDGE":"1406250000000000000000",
            "farmRewardsRISK" :"156250000000000000000"
        }
    ]
}